aizypy/AizyBot.py
aizypy/CandleData.py
aizypy/OrderManager.py
aizypy/TestEngine.py
aizypy/Trade.py
aizypy/WebSocketHandler.py
aizypy/__init__.py
aizypy-0.5.0.dist-info/METADATA
aizypy-0.5.0.dist-info/WHEEL
aizypy-0.5.0.dist-info/top_level.txt
aizypy-0.5.0.dist-info/RECORD
